setup.py
src/nose_pagerduty/NosePagerDuty.py
src/nose_pagerduty/__init__.py
src/nose_pagerduty.egg-info/PKG-INFO
src/nose_pagerduty.egg-info/SOURCES.txt
src/nose_pagerduty.egg-info/dependency_links.txt
src/nose_pagerduty.egg-info/entry_points.txt
src/nose_pagerduty.egg-info/requires.txt
src/nose_pagerduty.egg-info/top_level.txt