Metadata-Version: 1.1
Name: nose-pagerduty
Version: 0.2.0
Summary: PagerDuty alert plugin for nose
Home-page: https://github.com/lucamartinetti/nose-pagerduty
Author: Luca Martinetti
Author-email: luca@luca.io
License: BSD
Keywords: test nosetests nose nosetest plugin pagerduty alert
Platform: UNKNOWN
Classifier: Programming Language :: Python
Classifier: Topic :: Software Development :: Testing
